argocd/__init__.py
argocd/api_client.py
argocd/configuration.py
argocd/rest.py
argocd/api/__init__.py
argocd/api/account_service_api.py
argocd/api/application_service_api.py
argocd/api/application_set_service_api.py
argocd/api/certificate_service_api.py
argocd/api/cluster_service_api.py
argocd/api/gpg_key_service_api.py
argocd/api/notification_service_api.py
argocd/api/project_service_api.py
argocd/api/repo_creds_service_api.py
argocd/api/repository_service_api.py
argocd/api/session_service_api.py
argocd/api/settings_service_api.py
argocd/api/version_service_api.py
argocd/models/__init__.py
argocd/models/account_account.py
argocd/models/account_accounts_list.py
argocd/models/account_can_i_response.py
argocd/models/account_create_token_request.py
argocd/models/account_create_token_response.py
argocd/models/account_empty_response.py
argocd/models/account_token.py
argocd/models/account_update_password_request.py
argocd/models/account_update_password_response.py
argocd/models/application_application_manifest_query_with_files.py
argocd/models/application_application_manifest_query_with_files_wrapper.py
argocd/models/application_application_patch_request.py
argocd/models/application_application_resource_response.py
argocd/models/application_application_response.py
argocd/models/application_application_rollback_request.py
argocd/models/application_application_sync_request.py
argocd/models/application_application_sync_window.py
argocd/models/application_application_sync_windows_response.py
argocd/models/application_file_chunk.py
argocd/models/application_link_info.py
argocd/models/application_links_response.py
argocd/models/application_log_entry.py
argocd/models/application_managed_resources_response.py
argocd/models/application_operation_terminate_response.py
argocd/models/application_resource_actions_list_response.py
argocd/models/application_sync_options.py
argocd/models/applicationset_application_set_response.py
argocd/models/applicationv1alpha1_env_entry.py
python_argocd-0.0.1.dist-info/METADATA
python_argocd-0.0.1.dist-info/WHEEL
python_argocd-0.0.1.dist-info/top_level.txt
python_argocd-0.0.1.dist-info/RECORD
